Metadata-Version: 2.1
Name: printravisname
Version: 0.0.1
Summary: this is a trial package used for calculation.
Home-page: 
Author: RAVI CHANDRA A
Author-email: ravichandraananda@gmail.com
License: MIT
License-File: licence.txt
